runtime/serialization/__init__.py
runtime/serialization/decorators.py
runtime/serialization/hjson.py
runtime/serialization/interfaces.py
runtime/serialization/json.py
runtime/serialization/toml.py
runtime/serialization/yaml.py
runtime/serialization/core/base_formatter.py
runtime/serialization/core/base_serializer.py
runtime/serialization/core/circular_reference_exception.py
runtime/serialization/core/default_type_activator.py
runtime/serialization/core/deserialization_exception.py
runtime/serialization/core/deserialization_strategy.py
runtime/serialization/core/helpers.py
runtime/serialization/core/kwargs_type_activator.py
runtime/serialization/core/lazy.py
runtime/serialization/core/member.py
runtime/serialization/core/member_type.py
runtime/serialization/core/not_serializable_exception.py
runtime/serialization/core/primitives.py
runtime/serialization/core/readonly_exception.py
runtime/serialization/core/serialization_exception.py
runtime/serialization/core/serializer_attributes.py
runtime/serialization/core/serializer_attributes_registry.py
runtime/serialization/core/shared.py
runtime/serialization/core/threading.py
runtime/serialization/core/decorators/decorator_exception.py
runtime/serialization/core/decorators/ignore_decorator.py
runtime/serialization/core/decorators/serializable/serializable_attributes.py
runtime/serialization/core/decorators/serializable/serializable_decorator.py
runtime/serialization/core/decorators/serializable/serializable_delegate_decorator.py
runtime/serialization/core/decorators/type_resolving/dict_object.py
runtime/serialization/core/decorators/type_resolving/registry.py
runtime/serialization/core/decorators/type_resolving/resolvable_decorator.py
runtime/serialization/core/decorators/type_resolving/resolve_as_decorator.py
runtime/serialization/core/formats/hjson/formatter.py
runtime/serialization/core/formats/hjson/serializer.py
runtime/serialization/core/formats/json/formatter.py
runtime/serialization/core/formats/json/serializer.py
runtime_serialization-0.0.0b1.dist-info/licenses/LICENSE
runtime_serialization-0.0.0b1.dist-info/METADATA
runtime_serialization-0.0.0b1.dist-info/WHEEL
runtime_serialization-0.0.0b1.dist-info/top_level.txt
runtime_serialization-0.0.0b1.dist-info/RECORD
