Metadata-Version: 2.4
Name: runtime-serialization
Version: 0.0.0b1
Summary: Provides serialization to and from json, hjson, yaml and toml files.
Author-email: Anders Madsen <anders.madsen@alphavue.com>
License-Expression: MIT
Project-URL: repository, https://github.com/apmadsen/runtime-serialization
Keywords: windows,linux,serialization
Classifier: Development Status :: 5 - Production/Stable
Classifier: Development Status :: 6 - Mature
Classifier: Operating System :: Microsoft :: Windows
Classifier: Operating System :: POSIX :: Linux
Classifier: Intended Audience :: Developers
Classifier: Natural Language :: English
Classifier: Programming Language :: Python :: 3 :: Only
Classifier: Programming Language :: Python :: 3
Classifier: Programming Language :: Python :: 3.10
Classifier: Programming Language :: Python :: 3.11
Classifier: Programming Language :: Python :: 3.12
Classifier: Programming Language :: Python :: 3.13
Classifier: Programming Language :: Python
Classifier: Topic :: Software Development :: Libraries :: Python Modules
Classifier: Topic :: Software Development :: Libraries
Classifier: Typing :: Typed
Requires-Python: >=3.10
License-File: LICENSE
Requires-Dist: typing-utilities<0.2,>=0.1.0
Requires-Dist: runtime-reflection-lite<0.3,>=0.2.0
Requires-Dist: python-dateutil<2.10,>=2.9.0
Provides-Extra: test
Requires-Dist: pytest>=8.3; extra == "test"
Requires-Dist: pytest-cov>=6.1; extra == "test"
Requires-Dist: numpy<2.2,>=2.1.3; extra == "test"
Requires-Dist: PyYAML<6.1,>=6.0.2; extra == "test"
Requires-Dist: toml<0.11,>=0.10.2; extra == "test"
Requires-Dist: hjson<3.2,>=3.1.0; extra == "test"
Requires-Dist: delegate-events>=0.0.1; extra == "test"
Dynamic: license-file
